outfancy/__init__.py
outfancy/chart.py
outfancy/colors.py
outfancy/example_dataset.py
outfancy/table.py
outfancy/version.py
outfancy/widgets.py
outfancy/window.py
outfancy-0.8.0.dist-info/licenses/LICENSE
outfancy-0.8.0.dist-info/METADATA
outfancy-0.8.0.dist-info/WHEEL
outfancy-0.8.0.dist-info/top_level.txt
outfancy-0.8.0.dist-info/RECORD
