Metadata-Version: 2.4
Name: outfancy
Version: 0.8.0
Summary: Python3.11+ library to print tables and line charts in Terminal.
Author-email: "Carlos A. Planchón" <carlosandresplanchonprestes@gmail.com>
License-Expression: MIT
Project-URL: Repository, https://github.com/carlosplanchon/outfancy.git
Keywords: rendering,graphical,terminal,chart,graph
Classifier: Intended Audience :: Developers
Classifier: Topic :: Software Development :: Build Tools
Classifier: Programming Language :: Python :: 3.11
Requires-Python: >=3.11
License-File: LICENSE
Dynamic: license-file
